{
  "audioList": {
    "base": [
      {
        "title": "Sheets_Rustle",
        "mediaUri": "ms-appx:///Assets/sheets_rustling.mp3",
        "autoplay": false,
        "loop": true,
        "volume": 0.5
      },
      {
        "title": "Rain",
        "mediaUri": "ms-appx:///Assets/rain_interior.mp3",
        "autoplay": false,
        "loop": true,
        "volume": 0.4
      },
      {
        "title": "Traffic",
        "mediaUri": "ms-appx:///Assets/traffic_outside.mp3",
        "autoplay": false,
        "loop": false,
        "volume": 0.8
      },
      {
        "title": "Breathing",
        "mediaUri": "ms-appx:///Assets/breathing_calm.mp3",
        "autoplay": false,
        "loop": false,
        "volume": 0.5
      },
      {
        "title": "Out_of_Bed",
        "mediaUri": "ms-appx:///Assets/out_of_bed.mp3",
        "autoplay": false,
        "loop": false,
        "volume": 0.5
      },
      {
        "title": "Floor_Walk",
        "mediaUri": "ms-appx:///Assets/footsteps_tile.mp3",
        "autoplay": false,
        "loop": false,
        "volume": 0.5
      },
      {
        "title": "Tap_Water",
        "mediaUri": "ms-appx:///Assets/tap_water.mp3",
        "autoplay": false,
        "loop": false,
        "volume": 0.5
      },
      {
        "title": "Brushing_Teeth",
        "mediaUri": "ms-appx:///Assets/brushing_teeth.mp3",
        "autoplay": false,
        "loop": false,
        "volume": 0.5
      }
    ]
  }
}